ndonnx/__init__.py
ndonnx/_array.py
ndonnx/_array_tyarray_interop.py
ndonnx/_build.py
ndonnx/_constants.py
ndonnx/_deprecated.py
ndonnx/_dtypes.py
ndonnx/_elementwise.py
ndonnx/_experimental.py
ndonnx/_from_numpy_dtype.py
ndonnx/_funcs.py
ndonnx/_future.py
ndonnx/_infos.py
ndonnx/_namespace_info.py
ndonnx/_propagation.py
ndonnx/_schema.py
ndonnx/extensions.py
ndonnx/py.typed
ndonnx/types.py
ndonnx/_typed_array/__init__.py
ndonnx/_typed_array/_utils.py
ndonnx/_typed_array/datetime.py
ndonnx/_typed_array/dtype_independent_funcs.py
ndonnx/_typed_array/funcs.py
ndonnx/_typed_array/indexing.py
ndonnx/_typed_array/masked_onnx.py
ndonnx/_typed_array/onnx.py
ndonnx/_typed_array/ort_compat.py
ndonnx/_typed_array/typed_array.py
ndonnx-0.16.0.dist-info/licenses/LICENSE
ndonnx-0.16.0.dist-info/METADATA
ndonnx-0.16.0.dist-info/WHEEL
ndonnx-0.16.0.dist-info/top_level.txt
ndonnx-0.16.0.dist-info/RECORD
