Metadata-Version: 2.4
Name: ndonnx
Version: 0.16.0
Summary: ONNX backed array library compliant with Array API standard.
Author-email: Aditya Goel <agoel4512@gmail.com>, Christian Bourjau <christian.bourjau@quantco.com>
Project-URL: repository, https://github.com/quantco/ndonnx
Keywords: numpy,onnx,array-api
Classifier: License :: OSI Approved :: BSD License
Classifier: Operating System :: OS Independent
Classifier: Programming Language :: Python :: 3
Classifier: Programming Language :: Python :: 3.10
Classifier: Programming Language :: Python :: 3.11
Classifier: Programming Language :: Python :: 3.12
Classifier: Programming Language :: Python :: 3.13
Requires-Python: >=3.10
License-File: LICENSE
Requires-Dist: numpy
Requires-Dist: spox>=0.10
Requires-Dist: typing_extensions
Dynamic: license-file
